mymeme/__init__.py
mymeme/meme.py
mymeme-0.1.0.dist-info/licenses/LICENSE
mymeme-0.1.0.dist-info/METADATA
mymeme-0.1.0.dist-info/WHEEL
mymeme-0.1.0.dist-info/top_level.txt
mymeme-0.1.0.dist-info/RECORD
